{"data":{"markdownRemark":{"html":"<h1>Mijn portfolio's door de jaren heen</h1>\n<p>Hoewel ik nog niet zo lang geleden aan mijn opleiding informatica begon zijn mijn portfolio websites wel flink wat veranderd, qua design en qua intenties die ik met website wou bereiken. Hier laat ik in chronologische volgorde zien hoe mijn portfolio zich in de loop van mijn studie heeft ontwikkeld. </p>\n<p><button class=\"btn btn-green btn-sm\">button</button>\n<button class=\"btn btn-green btn-sm\">button</button>\n<button class=\"btn btn-green btn-sm\">button</button>\n<button class=\"btn btn-green btn-sm\">button</button>\n<button class=\"btn btn-green btn-sm\">button</button>\n<button class=\"btn btn-green btn-sm\">button</button></p>\n<p><a href=\"#\" class=\"btn btn-orange btn-lg\">button</a></p>","frontmatter":{"title":"Mijn portfolio's door de jaren heen","date":"2019-05-07","category":"blog"}}},"pageContext":{"isCreatedByStatefulCreatePages":false,"slug":"/Mijn-portfolios-door-de-jaren-heen/"}}